Multiprocessing_gRPC_Load_Balancer/__init__.py
Multiprocessing_gRPC_Load_Balancer/client.py
Multiprocessing_gRPC_Load_Balancer/interceptor.py
Multiprocessing_gRPC_Load_Balancer/prometheus.py
Multiprocessing_gRPC_Load_Balancer/redirect.py
Multiprocessing_gRPC_Load_Balancer/server.py
Multiprocessing_gRPC_Load_Balancer-0.0.2.dist-info/LICENSE
Multiprocessing_gRPC_Load_Balancer-0.0.2.dist-info/METADATA
Multiprocessing_gRPC_Load_Balancer-0.0.2.dist-info/WHEEL
Multiprocessing_gRPC_Load_Balancer-0.0.2.dist-info/top_level.txt
Multiprocessing_gRPC_Load_Balancer-0.0.2.dist-info/RECORD
