Metadata-Version: 2.1
Name: Multiprocessing_gRPC_Load_Balancer
Version: 0.0.2
Summary: Its a Load Balancer for multiprocessing gRPC Servers.
Home-page: https://github.com/Vault-of-Procrastination/Multiprocessing_gRPC_Load_Balancer
Download-URL: https://github.com/vault-of-procrastination/Multiprocessing_gRPC_Load_Balancer/tarball/0.0.1
Author: Vault-of-Procrastination
Author-email: vault_of_procrastination@outlook.com
Maintainer: Vault-of-Procrastination
Maintainer-email: vault_of_procrastination@outlook.com
License: Apache Software License 2.0
Keywords: grpc load balancer multiprocessing prometheus monitoring
Classifier: Development Status :: 4 - Beta
Classifier: Intended Audience :: Developers
Classifier: Operating System :: POSIX :: Linux
Classifier: Programming Language :: Python :: 3
Classifier: Programming Language :: Python :: 3.12
Classifier: Topic :: Communications
Classifier: Topic :: System :: Monitoring
Classifier: Topic :: Software Development :: Libraries
Classifier: Topic :: Software Development :: Libraries :: Python Modules
Classifier: License :: OSI Approved :: Apache Software License
Requires-Python: >=3.12
License-File: LICENSE
Requires-Dist: grpcio
Requires-Dist: grpcio-tools
Requires-Dist: prometheus-client
